pyvista_vtkjs/__init__.py
pyvista_vtkjs/cylinder_source.py
pyvista_vtkjs/install.py
pyvista_vtkjs/plotter.py
pyvista_vtkjs-0.0.2.dist-info/METADATA
pyvista_vtkjs-0.0.2.dist-info/WHEEL
pyvista_vtkjs-0.0.2.dist-info/top_level.txt
pyvista_vtkjs-0.0.2.dist-info/RECORD
